<?xml version="1.0" encoding="utf-8"?>
<layout onLaunch="launch" onVolumeUp="volume_up" onVolumeDown="volume_down" onResume="play" onPause="pause" color="orange">
  <grid>
    <row>
      <label id="info" text="Awesome Movie" textAlign="center" />
    </row>
    <row>
      <button icon="vdown" onTap="volume_down" />
      <button icon="vmute" onTap="volume_mute" />
      <button icon="vup" onTap="volume_up" />
    </row>
	<row>
		<button text="-10s" ontap="back" />
		<button text="+10s" ontap="forward" />
	</row>
    <row>
      <button icon="previous" onTap="previous" />
	  <button icon="fullscreen" ontap="fullscreen" />
      <button icon="next" onTap="next" />
    </row>
    <row>
      <button icon="stop" onTap="stop" />
      <button icon="playpause" onTap="play_pause" />
    </row>
  </grid>
</layout>